{
  "intent_id": "CHITCHAT",
  "name": "CHITCHAT (Casual Conversation)",
  "description": "Intent for casual greetings and small talk",
  "category": "Social",
  "priority": "low",
  "keywords": {
    "english": [
      "hello",
      "hi",
      "hey",
      "good morning",
      "good afternoon",
      "good evening",
      "thanks",
      "thank you",
      "bye",
      "goodbye",
      "how are you",
      "nice to meet you",
      "what's up",
      "howdy",
      "greetings",
      "see you",
      "later",
      "cheers"
    ],
    "portuguese": [
      "olá",
      "oi",
      "bom dia",
      "boa tarde",
      "boa noite",
      "obrigado",
      "obrigada",
      "tchau",
      "até logo",
      "como vai",
      "prazer",
      "tudo bem",
      "e aí",
      "fala",
      "valeu",
      "até mais"
    ],
    "spanish": [
      "hola",
      "buenos días",
      "buenas tardes",
      "buenas noches",
      "gracias",
      "adiós",
      "hasta luego",
      "cómo estás",
      "mucho gusto",
      "qué tal",
      "saludos",
      "nos vemos",
      "chao"
    ]
  },
  "patterns": {
    "english": [
      "^(hello|hi|hey|howdy|greetings|yo)(!)?$",
      "^(good)\\s+(morning|afternoon|evening|night)(!)?$",
      "^(thanks|thank you|thx|cheers)(!)?$",
      "^(bye|goodbye|see you|later|farewell)(!)?$",
      "^(how are you|how's it going|what's up|how do you do)(\\?)?$",
      "^(nice|pleased|great)\\s+(to meet you|meeting you)(!)?$",
      "^(have a)\\s+(good|nice|great)\\s+(day|evening|night|one)(!)?$"
    ],
    "portuguese": [
      "^(olá|oi|e aí|fala|eae)(!)?$",
      "^(bom dia|boa tarde|boa noite)(!)?$",
      "^(obrigado|obrigada|valeu|agradeço)(!)?$",
      "^(tchau|até logo|até mais|adeus|falou)(!)?$",
      "^(como vai|tudo bem|tudo certo|como você está)(\\?)?$",
      "^(prazer|prazer em conhecer)(!)?$",
      "^(tenha um|bom)\\s+(bom|boa)\\s+(dia|tarde|noite)(!)?$"
    ],
    "spanish": [
      "^(hola|hey|saludos)(!)?$",
      "^(buenos días|buenas tardes|buenas noches)(!)?$",
      "^(gracias|muchas gracias)(!)?$",
      "^(adiós|hasta luego|nos vemos|chao)(!)?$",
      "^(cómo estás|qué tal|cómo te va)(\\?)?$",
      "^(mucho gusto|encantado|un placer)(!)?$",
      "^(que tengas|buen)\\s+(un buen|buena)\\s+(día|tarde|noche)(!)?$"
    ]
  },
  "examples": {
    "english": [
      "Hello!",
      "Hi",
      "Good morning",
      "Good afternoon",
      "Good evening",
      "Thanks!",
      "Thank you",
      "Bye",
      "Goodbye",
      "How are you?",
      "Nice to meet you",
      "What's up?",
      "Have a good day!",
      "See you later"
    ],
    "portuguese": [
      "Olá!",
      "Oi",
      "Bom dia",
      "Boa tarde",
      "Boa noite",
      "Obrigado!",
      "Valeu",
      "Tchau",
      "Até logo",
      "Como vai?",
      "Prazer",
      "Tudo bem?",
      "Tenha um bom dia!",
      "Até mais"
    ],
    "spanish": [
      "¡Hola!",
      "Hey",
      "Buenos días",
      "Buenas tardes",
      "Buenas noches",
      "¡Gracias!",
      "Adiós",
      "Hasta luego",
      "¿Cómo estás?",
      "Mucho gusto",
      "¿Qué tal?",
      "¡Que tengas un buen día!",
      "Nos vemos"
    ]
  }
}
